pypi_learn/__init__.py
pypi_learn/youtube_srt_mp3.py
pypi_learn/crop_mp3_srt/crop_mp3_srt.py
pypi_learn/helper/helper.py
pypi_learn-0.0.7.dist-info/LICENSE
pypi_learn-0.0.7.dist-info/METADATA
pypi_learn-0.0.7.dist-info/WHEEL
pypi_learn-0.0.7.dist-info/entry_points.txt
pypi_learn-0.0.7.dist-info/top_level.txt
pypi_learn-0.0.7.dist-info/RECORD
