Metadata-Version: 2.1
Name: pypi-learn
Version: 0.0.7
Summary: Generates a dataset for the Turkish speech recognition.
Home-page: https://github.com/IoT-Ignite/pypi_learn
Author: ARDIC R&D
Author-email: yavuz.erzurumlu@ardictech.com
License: MIT
Keywords: dataset,speech recognition,srt,youtube srt
Platform: UNKNOWN
Classifier: Programming Language :: Python :: 3
Classifier: Programming Language :: Python :: 3.6
Classifier: Programming Language :: Python :: 3.7
Classifier: Programming Language :: Python :: 3.8
Classifier: License :: OSI Approved :: Apache Software License
Classifier: Intended Audience :: Developers
Requires-Dist: youtube-channel-transcript-api
Requires-Dist: youtube-transcript-api
Requires-Dist: youtube-dl
Requires-Dist: launchpadlib
